zipsar/__init__.py
zipsar/main.py
zipsar-0.1.0.dist-info/METADATA
zipsar-0.1.0.dist-info/WHEEL
zipsar-0.1.0.dist-info/top_level.txt
zipsar-0.1.0.dist-info/RECORD
